nrtest_swmm/__init__.py
nrtest_swmm/output_reader.py
nrtest_swmm-0.7.0.data/scripts/report-diff
nrtest_swmm-0.7.0.dist-info/METADATA
nrtest_swmm-0.7.0.dist-info/WHEEL
nrtest_swmm-0.7.0.dist-info/entry_points.txt
nrtest_swmm-0.7.0.dist-info/top_level.txt
nrtest_swmm-0.7.0.dist-info/RECORD
